quanTrade/__init__.py
quanTrade/client.py
quanTrade/client_IBKR.py
quanTrade/client_MT4.py
quanTrade/distant.py
quanTrade/system.py
quanTrade/trader.py
quanTrade/utils.py
quanTrade/ibapi/__init__.py
quanTrade/ibapi/account_summary_tags.py
quanTrade/ibapi/client.py
quanTrade/ibapi/comm.py
quanTrade/ibapi/commission_report.py
quanTrade/ibapi/common.py
quanTrade/ibapi/connection.py
quanTrade/ibapi/contract.py
quanTrade/ibapi/decoder.py
quanTrade/ibapi/enum_implem.py
quanTrade/ibapi/errors.py
quanTrade/ibapi/execution.py
quanTrade/ibapi/message.py
quanTrade/ibapi/news.py
quanTrade/ibapi/object_implem.py
quanTrade/ibapi/order.py
quanTrade/ibapi/order_condition.py
quanTrade/ibapi/order_state.py
quanTrade/ibapi/orderdecoder.py
quanTrade/ibapi/reader.py
quanTrade/ibapi/scanner.py
quanTrade/ibapi/server_versions.py
quanTrade/ibapi/softdollartier.py
quanTrade/ibapi/tag_value.py
quanTrade/ibapi/ticktype.py
quanTrade/ibapi/utils.py
quanTrade/ibapi/wrapper.py
q26_quanTrader-0.1.2.dist-info/LICENSE.md
q26_quanTrader-0.1.2.dist-info/METADATA
q26_quanTrader-0.1.2.dist-info/WHEEL
q26_quanTrader-0.1.2.dist-info/top_level.txt
q26_quanTrader-0.1.2.dist-info/RECORD
