Metadata-Version: 2.1
Name: q26-quanTrader
Version: 0.1.2
Summary: A python package for live trading
Home-page: https://github.com/LoannData/Q26_QuanTrader.git
Author: Loann Brahimi
Author-email: loann.brahimi@data-sciences.io
License: UNKNOWN
Platform: UNKNOWN
Classifier: Programming Language :: Python :: 3
Classifier: License :: OSI Approved :: MIT License
Classifier: Operating System :: OS Independent
Requires-Python: >=3.6
License-File: LICENSE.md
Requires-Dist: python-telegram-bot
